nlpfileio/__init__.py
nlpfileio/cli.py
nlpfileio/config.ini
nlpfileio/sample.txt
nlpfileio/sample_data/sample.csv
nlpfileio/sample_data/sample.txt
nlpfileio/services.py
nlpfileio/setup.py
nlpfileio/test_outputs/cleaned_sentences.txt
nlpfileio/test_outputs/normalized_sentences.txt
nlpfileio/test_outputs/sentiments_sentences.txt
nlpfileio/test_outputs/stemmed_sentences.txt
nlpfileio-0.1.1.dist-info/METADATA
nlpfileio-0.1.1.dist-info/WHEEL
nlpfileio-0.1.1.dist-info/entry_points.txt
nlpfileio-0.1.1.dist-info/RECORD
