Metadata-Version: 2.3
Name: nlpfileio
Version: 0.1.1
Summary: An open-source Python library for CLI and NLP tasks
License: MIT
Keywords: cli,nlp,text,utilities
Author: Fatemeh Ahmadzadeh
Author-email: ahmadzade920@gmail.com
Requires-Python: >=3.10
Classifier: License :: OSI Approved :: MIT License
Classifier: Programming Language :: Python :: 3
Classifier: Programming Language :: Python :: 3.10
Classifier: Programming Language :: Python :: 3.11
Classifier: Programming Language :: Python :: 3.12
Classifier: Programming Language :: Python :: 3.13
Requires-Dist: click
Requires-Dist: click-config-file
Requires-Dist: click-help-colors
Requires-Dist: click-params
Requires-Dist: colorama
Requires-Dist: commonmark
Requires-Dist: pandas
Requires-Dist: pyfiglet
Requires-Dist: rich
Requires-Dist: setuptools
Requires-Dist: spacy
Requires-Dist: textblob
